django_signal_notifier/__init__.py
django_signal_notifier/admin.py
django_signal_notifier/apps.py
django_signal_notifier/exceptions.py
django_signal_notifier/message_templates.py
django_signal_notifier/messengers.py
django_signal_notifier/models.py
django_signal_notifier/settings.py
django_signal_notifier/signals.py
django_signal_notifier/management/commands/run_builtin_signal_trigger.py
django_signal_notifier/management/commands/run_message_template.py
django_signal_notifier/management/commands/run_trigger.py
django_signal_notifier/management/commands/test_messenger.py
django_signal_notifier/migrations/0001_initial.py
django_signal_notifier/migrations/0002_auto_20191201_1040.py
django_signal_notifier/migrations/0003_auto_20200204_1205.py
django_signal_notifier/migrations/0004_auto_20200309_0114.py
django_signal_notifier/migrations/0005_auto_20210321_1132.py
django_signal_notifier/migrations/__init__.py
django_signal_notifier/templates/admin/django_signal_notifier/trigger/change_form.html
django_signal_notifier/templates/message_templates/base.html
django_signal_notifier/templates/message_templates/simple_print_message.html
django_signal_notifier/templates/message_templates/simple_telegram_message.html
django_signal_notifier/tests/__init__.py
django_signal_notifier/tests/test_backend.py
django_signal_notifier/tests/test_init.py
django_signal_notifier/tests/test_subscription.py
django_signal_notifier/tests/test_trigger.py
django_signal_notifier-0.2.1.dist-info/LICENSE
django_signal_notifier-0.2.1.dist-info/METADATA
django_signal_notifier-0.2.1.dist-info/WHEEL
django_signal_notifier-0.2.1.dist-info/top_level.txt
django_signal_notifier-0.2.1.dist-info/RECORD
