Metadata-Version: 2.1
Name: django-signal-notifier
Version: 0.2.1
Summary: DSN or django-signal-notifier is a Django package to send message or notification based on the Django's signals triggering
Home-page: https://github.com/hadi2f244/django-signal-notifier
Author: Mohammad Hadi Azaddel
Author-email: m.h.azaddel@gmail.com
License: BSD-3-Clause
Project-URL: Documentation, https://django-signal-notifier.readthedocs.io/
Project-URL: Source, https://github.com/hadi2f244/django-signal-notifier
Project-URL: Tracker, https://github.com/hadi2f244/django-signal-notifier/issues
Keywords: django,notification,signal
Platform: UNKNOWN
Classifier: Development Status :: 3 - Alpha
Classifier: Environment :: Web Environment
Classifier: Framework :: Django
Classifier: Framework :: Django
Classifier: Intended Audience :: Developers
Classifier: License :: OSI Approved :: BSD License
Classifier: Operating System :: OS Independent
Classifier: Programming Language :: Python
Classifier: Programming Language :: Python :: 3
Classifier: Programming Language :: Python :: 3.5
Classifier: Programming Language :: Python :: 3.6
Classifier: Programming Language :: Python :: 3.7
Classifier: Programming Language :: Python :: 3 :: Only
Classifier: Topic :: Internet :: WWW/HTTP
Classifier: Topic :: Internet :: WWW/HTTP :: Dynamic Content
Classifier: Topic :: Software Development
Classifier: Topic :: Software Development :: Libraries :: Application Frameworks
Requires-Dist: Django (<3.1Telethon>=1.16.4,>=1.8)
